kera.py
kera-1.2.1.dist-info/entry_points.txt
kera-1.2.1.dist-info/licenses/LICENSE
kera-1.2.1.dist-info/WHEEL
kera-1.2.1.dist-info/METADATA
kera-1.2.1.dist-info/RECORD
