Metadata-Version: 2.4
Name: kera
Version: 1.2.1
Summary: Fill template files with structured data
Author-email: C Wiebe <ctwiebe23@gmail.com>
License-Expression: MIT
License-File: LICENSE
Requires-Dist: pyyaml
Project-URL: Github, https://github.com/ctwiebe23/kera
Project-URL: Home, https://ctwiebe23.github.io/kera
